LICENSE.txt
README.md
setup.py
mp_basic_calculator/__init__.py
mp_basic_calculator/calculator.py
mp_basic_calculator.egg-info/PKG-INFO
mp_basic_calculator.egg-info/SOURCES.txt
mp_basic_calculator.egg-info/dependency_links.txt
mp_basic_calculator.egg-info/requires.txt
mp_basic_calculator.egg-info/top_level.txt
mp_basic_calculator/tests/__init__.py
mp_basic_calculator/tests/test_addition.py
mp_basic_calculator/tests/test_division.py
mp_basic_calculator/tests/test_get_memory.py
mp_basic_calculator/tests/test_memory_reset.py
mp_basic_calculator/tests/test_multiplication.py
mp_basic_calculator/tests/test_subtraction.py
mp_basic_calculator/tests/test_take_nth_root.py