Metadata-Version: 2.1
Name: mp-basic-calculator
Version: 0.4
License-File: LICENSE.txt
